geeznum/__init__.py
geeznum/version.py
geeznum-1.0.dist-info/LICENSE
geeznum-1.0.dist-info/METADATA
geeznum-1.0.dist-info/WHEEL
geeznum-1.0.dist-info/top_level.txt
geeznum-1.0.dist-info/RECORD
