Metadata-Version: 2.1
Name: geeznum
Version: 1.0
Summary: A python package that converts arabic number to geez number
Home-page: https://github.com/natanimn/GeezNumber
Author: Natanim Negash
Author-email: natanimn@yahoo.com
License: MIT
Keywords: number,geez number,number convertor,python number,geez
License-File: LICENSE
